irdata/__init__.py
irdata/data.py
irdata/java.py
irdata/signatures.py
irdata/xmldata.py
irdata-0.2.5.dist-info/LICENSE
irdata-0.2.5.dist-info/WHEEL
irdata-0.2.5.dist-info/METADATA
irdata-0.2.5.dist-info/RECORD
