Metadata-Version: 2.1
Name: irdata
Version: 0.2.5
Summary: Data processing library for iRefIndex
Home-page: https://github.com/vibbits/irdata
License: GPL-3.0-or-later
Author: VIB Bioinformatics Core Facility
Author-email: bits@vib.be
Requires-Python: >=3.7,<4.0
Classifier: License :: OSI Approved :: GNU General Public License v3 or later (GPLv3+)
Classifier: Programming Language :: Python :: 3
Classifier: Programming Language :: Python :: 3.10
Classifier: Programming Language :: Python :: 3.7
Classifier: Programming Language :: Python :: 3.8
Classifier: Programming Language :: Python :: 3.9
Requires-Dist: defusedxml (>=0.7.1,<0.8.0)
Project-URL: Repository, https://github.com/vibbits/irdata
